phcovid/__init__.py
phcovid/constants.py
phcovid/phcovid.py
phcovid/phcovid_network.py
phcovid/phcovid_plot.py
phcovid/data_extractor/__init__.py
phcovid/data_extractor/arcgis.py
phcovid/data_extractor/dsph_gsheet.py
phcovid-0.0.2.10.dist-info/LICENSE
phcovid-0.0.2.10.dist-info/METADATA
phcovid-0.0.2.10.dist-info/WHEEL
phcovid-0.0.2.10.dist-info/top_level.txt
phcovid-0.0.2.10.dist-info/RECORD
