Metadata-Version: 2.1
Name: phcovid
Version: 0.0.2.10
Summary: Get PH COVID data in only two lines of code!
Home-page: https://github.com/enzoampil/phcovid
Author: Lorenzo Ampil
Author-email: lorenzo.ampil@gmail.com
License: UNKNOWN
Platform: UNKNOWN
Classifier: Programming Language :: Python :: 3
Classifier: License :: OSI Approved :: MIT License
Classifier: Operating System :: OS Independent
Requires-Dist: matplotlib (==3.1.2)
Requires-Dist: pandas (==1.0.3)
Requires-Dist: beautifulsoup4 (==4.8.2)
